Metadata-Version: 2.1
Name: st2client
Version: 3.9.0
Summary: Python client library and CLI for the StackStorm (st2) event-driven automation platform.
Home-page: https://stackstorm.com/
Author: StackStorm
Author-email: info@stackstorm.com
License: Apache-2.0
Project-URL: Pack Exchange, https://exchange.stackstorm.org
Project-URL: Repository, https://github.com/StackStorm/st2
Project-URL: Documentation, https://docs.stackstorm.com
Project-URL: Community, https://stackstorm.com/community-signup
Project-URL: Questions, https://github.com/StackStorm/st2/discussions
Project-URL: Donate, https://funding.communitybridge.org/projects/stackstorm
Project-URL: News/Blog, https://stackstorm.com/blog
Project-URL: Security, https://docs.stackstorm.com/latest/security.html
Project-URL: Bug Reports, https://github.com/StackStorm/st2/issues
Platform: UNKNOWN
Classifier: Development Status :: 5 - Production/Stable
Classifier: Intended Audience :: Information Technology
Classifier: Intended Audience :: Developers
Classifier: Intended Audience :: System Administrators
Classifier: Operating System :: POSIX :: Linux
Classifier: Programming Language :: Python
Classifier: Programming Language :: Python :: 3
Classifier: Programming Language :: Python :: 3.9
Classifier: Programming Language :: Python :: 3.10
Classifier: Programming Language :: Python :: 3.11
Requires-Dist: argcomplete==3.6.2
Requires-Dist: cffi==1.17.1
Requires-Dist: chardet==5.2.0
Requires-Dist: cryptography==43.0.3
Requires-Dist: editor==1.6.6
Requires-Dist: importlib-metadata==8.5.0
Requires-Dist: jsonpath-rw==1.4.0
Requires-Dist: jsonschema==3.2.0
Requires-Dist: orjson==3.10.15
Requires-Dist: prettytable==3.11.0
Requires-Dist: prompt-toolkit==3.0.52
Requires-Dist: pyOpenSSL<25.2
Requires-Dist: pygments==2.19.2
Requires-Dist: pysocks
Requires-Dist: python-dateutil==2.9.0.post0
Requires-Dist: pytz==2025.2
Requires-Dist: pyyaml==6.0.3
Requires-Dist: requests==2.32.4
Requires-Dist: six==1.17.0
Requires-Dist: sseclient-py==1.8.0
Requires-Dist: urllib3==2.2.3
Requires-Dist: zipp==3.20.2
Requires-Dist: typing-extensions>=4.13.2; python_version < "3.11"
